justfile/__init__.py
justfile/exception.py
justfile/io.py
justfile/tests/__init__.py
justfile-0.0.1a0.dist-info/LICENSE
justfile-0.0.1a0.dist-info/WHEEL
justfile-0.0.1a0.dist-info/METADATA
justfile-0.0.1a0.dist-info/RECORD
